{
  "pixelCentral": [272,220],
  "pixelPetaloMasAlejado":[224,257],
  "pixelCentroMasAlejado":[36,45],

  "colorPetaloPreferido":[[48,9,118],[125,87,160],[255,253,255],[145,167,131]],
  "colorCentroPreferido":[[206,213,21],[13,14,8],[97,95,21]],
  "petalColorDifference": 60,
  "centerColorDifference": 80,

  "petalOutlineIncrease" :  1,
  "centerOutlineIncrease" :  -1,
  "petalOutlineAxis": 1,
  "centerOutlineAxis": 0,

  "petalOutlineInitPos": [272, 19],
  "petalOutlineEndPos": [335, 160],
  "centerOutlineInitPos": [303, 227],
  "centerOutlineEndPos": [274, 258],

  "numeroPetalos": 5
}